[{"word":"yeah","startTime":"0.0","endTime":"0.2","confidence":0.9025633931159973},{"word":"which","startTime":"0.2","endTime":"1.1","confidence":0.9454663395881653},{"word":"is","startTime":"1.1","endTime":"1.2","confidence":0.9876290559768677},{"word":"why","startTime":"1.2","endTime":"1.4","confidence":0.9876290559768677},{"word":"we","startTime":"1.4","endTime":"1.6","confidence":0.9876290559768677},{"word":"need","startTime":"1.6","endTime":"1.7","confidence":0.9876290559768677},{"word":"a","startTime":"1.7","endTime":"1.8","confidence":0.9876290559768677},{"word":"video","startTime":"1.8","endTime":"2.0","confidence":0.9876290559768677},{"word":"as","startTime":"2.0","endTime":"3.0","confidence":0.9876290559768677}]