[{"word":"I'm","startTime":"2.0","endTime":"2.4","confidence":0.9356478452682495},{"word":"glad","startTime":"2.4","endTime":"2.7","confidence":0.9497033953666687},{"word":"you're","startTime":"2.7","endTime":"2.9","confidence":0.9496240019798279},{"word":"the","startTime":"3.3","endTime":"3.5","confidence":1},{"word":"same","startTime":"3.5","endTime":"3.7","confidence":0.9876290559768677},{"word":"experiences","startTime":"3.7","endTime":"5.0","confidence":0.9063900709152222},{"word":"and","startTime":"5.0","endTime":"5.6","confidence":1},{"word":"good","startTime":"5.9","endTime":"6.1","confidence":0.9210922718048096},{"word":"for","startTime":"6.1","endTime":"6.2","confidence":0.9652726650238037}]