[{"word":"I","startTime":"0.0","endTime":"0.1","confidence":0.9876290559768677},{"word":"want","startTime":"0.1","endTime":"0.3","confidence":0.9876290559768677},{"word":"to","startTime":"0.3","endTime":"0.4","confidence":1},{"word":"be","startTime":"0.4","endTime":"0.5","confidence":0.9810519218444824},{"word":"Nunu","startTime":"0.5","endTime":"0.9","confidence":0.9597684741020203},{"word":"and","startTime":"0.9","endTime":"1.0","confidence":0.9385831356048584},{"word":"willump","startTime":"1.0","endTime":"1.4","confidence":0.9385834336280823},{"word":"bro","startTime":"1.4","endTime":"1.8","confidence":0.9220167994499207}]